racs_tools/__init__.py
racs_tools/au2.py
racs_tools/beamcon_2D.py
racs_tools/beamcon_3D.py
racs_tools/convolve_uv.py
racs_tools/gaussft.py
racs_tools/getnoise_list.py
racs_tools/logging.py
racs_tools/parallel.py
racs_tools-4.3.0.dist-info/LICENSE
racs_tools-4.3.0.dist-info/METADATA
racs_tools-4.3.0.dist-info/WHEEL
racs_tools-4.3.0.dist-info/entry_points.txt
racs_tools-4.3.0.dist-info/RECORD
