Metadata-Version: 2.3
Name: racs-tools
Version: 4.3.0
Summary: Useful scripts for RACS.
License: BSD
Author: Alec Thomson
Requires-Python: >=3.10
Classifier: License :: Other/Proprietary License
Classifier: Programming Language :: Python :: 3
Classifier: Programming Language :: Python :: 3.10
Classifier: Programming Language :: Python :: 3.11
Classifier: Programming Language :: Python :: 3.12
Classifier: Programming Language :: Python :: 3.13
Provides-Extra: mpi
Requires-Dist: astropy (>=6)
Requires-Dist: mpi4py (>=3) ; extra == "mpi"
Requires-Dist: numba
Requires-Dist: numpy (>=2)
Requires-Dist: radio_beam (>=0.3.8)
Requires-Dist: scipy
Requires-Dist: spectral_cube (>=0.6.3)
Requires-Dist: tqdm
